src/__init__.py
src/main/__init__.py
src/main/python/__init__.py
src/main/python/main.py
src/main/python/configuration/__init__.py
src/main/python/configuration/config.py
src/main/python/io_operations/__init__.py
src/main/python/io_operations/make_directory.py
src/main/python/io_operations/month_mapping.py
src/main/python/logs/__init__.py
src/main/python/logs/date_time.py
src/main/python/logs/logger.py
src/main/python/services/__init__.py
src/main/python/services/save_crypto_currencies_exchange_rates.py
src/main/python/services/save_isin_mapping.py
src/main/python/services/save_reports_from_caceis.py
src/main/python/services/save_reports_morrison.py
src/main/python/services/save_reports_steubing.py
src/main/python/services/send_caceis_japan_trades.py
src/main/python/services/functions/__init__.py
src/main/python/services/functions/mounted_directory.py
src/main/python/services/functions/save_attachment.py
src/main/python/services/functions/send_email.py
src/main/test/__init__.py
src/main/test/configuration/TestConfig.py
src/main/test/configuration/__init__.py
src/main/test/io_operations/TestIOOperations.py
src/main/test/io_operations/__init__.py
src/main/test/logs/TestDateTime.py
src/main/test/logs/__init__.py
src/main/test/services/TestISINMapping.py
src/main/test/services/TestMountDirectory.py
src/main/test/services/__init__.py
exchange_web_server-1.1.0.dist-info/METADATA
exchange_web_server-1.1.0.dist-info/WHEEL
exchange_web_server-1.1.0.dist-info/top_level.txt
exchange_web_server-1.1.0.dist-info/RECORD
