Metadata-Version: 2.1
Name: exchange-web-server
Version: 1.1.0
Summary: Send/Save Emails & Attachments via Outlook
Author: Valentin Baier
Author-email: valentin_baier@gmx.de
Keywords: python,email,outlook,send,send email,save,save email
Classifier: Development Status :: 1 - Planning
Classifier: Intended Audience :: Developers
Classifier: Programming Language :: Python :: 3
Classifier: Operating System :: Unix
Classifier: Operating System :: MacOS :: MacOS X
Classifier: Operating System :: Microsoft :: Windows
Requires-Dist: exchangelib
